mwpy/__init__.py
mwpy/_api.py
mwpy/_version.py
mwpy-0.3.dist-info/METADATA
mwpy-0.3.dist-info/WHEEL
mwpy-0.3.dist-info/top_level.txt
mwpy-0.3.dist-info/zip-safe
mwpy-0.3.dist-info/RECORD
