Metadata-Version: 2.1
Name: mwpy
Version: 0.3
Summary: An async MediaWiki client using trio and asks.
Home-page: https://github.com/5j9/mwpy
Author: 5j9
Author-email: 5j9@users.noreply.github.com
License: GNU General Public License v3 (GPLv3)
Platform: UNKNOWN
Classifier: Development Status :: 1 - Planning
Classifier: Intended Audience :: Developers
Classifier: License :: OSI Approved :: GNU General Public License v3 (GPLv3)
Classifier: Natural Language :: English
Classifier: Programming Language :: Python :: 3.5
Classifier: Programming Language :: Python :: 3.6
Classifier: Programming Language :: Python :: 3.7
Classifier: Programming Language :: Python :: 3.8
Classifier: Environment :: Web Environment
Classifier: Framework :: Trio
Requires-Python: >=3.5
Requires-Dist: trio
Requires-Dist: asks
